implicit_globals.py
implicit_globals-1.0.1.dist-info/LICENSE
implicit_globals-1.0.1.dist-info/METADATA
implicit_globals-1.0.1.dist-info/WHEEL
implicit_globals-1.0.1.dist-info/top_level.txt
implicit_globals-1.0.1.dist-info/RECORD
