Metadata-Version: 2.1
Name: implicit-globals
Version: 1.0.1
Summary: A decorator that provides a way to override a function's global variables
Home-page: https://github.com/sebdevine/implicit_globals
Author: Sebastien Devine
Author-email: sebdevine@users.noreply.github.com
License: MIT
Keywords: implicit globals decorator functional
Platform: UNKNOWN
Classifier: Development Status :: 4 - Beta
Classifier: Intended Audience :: Developers
Classifier: License :: OSI Approved :: MIT License
Classifier: Programming Language :: Python :: 3.6
Classifier: Programming Language :: Python :: 3.7
Classifier: Programming Language :: Python :: 3.8
Classifier: Topic :: Software Development
Requires-Python: >=3.6
License-File: LICENSE
